fgmk/Editor.py
fgmk/__init__.py
fgmk/__main__.py
fgmk/action_dialog.py
fgmk/actions_wdgt.py
fgmk/base_tile.py
fgmk/cmd.py
fgmk/configure_project.py
fgmk/copypaste.py
fgmk/current_project.py
fgmk/editor_mainwindow_menus.py
fgmk/fifl.py
fgmk/flowlayout.py
fgmk/game_init.py
fgmk/game_server.py
fgmk/getdata.py
fgmk/help.py
fgmk/item_editor.py
fgmk/miniWdgt.py
fgmk/palette_editor.py
fgmk/persona.py
fgmk/tMat.py
fgmk/tile_charaset.py
fgmk/tile_set.py
fgmk/tools_logic.py
fgmk/data/actionsList.json
fgmk/data/animTile.png
fgmk/data/basegame.tar.gz
fgmk/data/clearTile.png
fgmk/data/collisionTiles.png
fgmk/data/default.pal.json
fgmk/data/emptyTile.png
fgmk/data/eventTiles.png
fgmk/data/example.tar.gz
fgmk/data/fgmk.qch
fgmk/data/fgmk.qhc
fgmk/data/icon.png
fgmk/data/icon_max.png
fgmk/data/icon_max_p1.png
fgmk/data/icon_zero.png
fgmk/data/indicativeTiles.png
fgmk/data/map_explorer_icons.png
fgmk/data/tile.png
fgmk/data/tools.png
fgmk/data/actions/ELSE.png
fgmk/data/actions/END.png
fgmk/data/actions/IF.png
fgmk/data/actions/addItem.png
fgmk/data/actions/alert.png
fgmk/data/actions/battle.png
fgmk/data/actions/blockInput.png
fgmk/data/actions/changeAllTiles.png
fgmk/data/actions/changePan.png
fgmk/data/actions/changePlayerAnimation.png
fgmk/data/actions/changeTile.png
fgmk/data/actions/charAutoDelete.png
fgmk/data/actions/dropItem.png
fgmk/data/actions/fadeIn.png
fgmk/data/actions/fadeOut.png
fgmk/data/actions/insideOutside.png
fgmk/data/actions/moveChara.png
fgmk/data/actions/noEffect.png
fgmk/data/actions/playAnimationInMap.png
fgmk/data/actions/playMusic.png
fgmk/data/actions/playSound.png
fgmk/data/actions/questionBox.png
fgmk/data/actions/rain.png
fgmk/data/actions/setCharaInvisibility.png
fgmk/data/actions/setVar.png
fgmk/data/actions/shakeScreen.png
fgmk/data/actions/showText.png
fgmk/data/actions/stopMusic.png
fgmk/data/actions/teleport.png
fgmk/data/actions/teleportInPlace.png
fgmk-0.7.4.dist-info/DESCRIPTION.rst
fgmk-0.7.4.dist-info/METADATA
fgmk-0.7.4.dist-info/RECORD
fgmk-0.7.4.dist-info/WHEEL
fgmk-0.7.4.dist-info/entry_points.txt
fgmk-0.7.4.dist-info/metadata.json
fgmk-0.7.4.dist-info/top_level.txt
