Metadata-Version: 2.0
Name: fgmk
Version: 0.7.4
Summary: A PyQt5 Maker to generate a RPG Javascript game.
Home-page: https://github.com/ericoporto/fgmk
Author: Erico Vieira Porto
Author-email: ericoporto2008@gmail.com
License: GPLv2
Download-URL: https://github.com/ericoporto/fgmk/tarball/0.7.4
Keywords: game development
Platform: UNKNOWN
Classifier: Development Status :: 3 - Alpha
Classifier: Intended Audience :: Developers
Classifier: Topic :: Games/Entertainment :: Role-Playing
Classifier: License :: OSI Approved :: GNU General Public License v2 (GPLv2)
Classifier: Programming Language :: Python :: 2.7
Classifier: Programming Language :: Python :: 3
Classifier: Programming Language :: Python :: 3.4
Classifier: Programming Language :: Python :: 3.5
Requires-Dist: numpy
Requires-Dist: pillow
Requires-Dist: pyqt5
